<?xml version="1.0" encoding="utf-8"?>
<!DOCTYPE hibernate-mapping PUBLIC "-//Hibernate/Hibernate Mapping DTD 3.0//EN"
"http://hibernate.sourceforge.net/hibernate-mapping-3.0.dtd">
<!-- 
    Mapping file autogenerated by MyEclipse Persistence Tools
-->
<hibernate-mapping>
    <class name="com.topcheer.oss.log.bo.Z020LogClear" table="z020_log_clear" catalog="oss">
        <id name="logId" type="java.lang.String">
            <column name="Log_Id" length="32" />
            <generator class="assigned" />
        </id>
        <property name="paraType" type="java.lang.String">
            <column name="Para_Type" length="10" />
        </property>
        <property name="paraValue" type="java.lang.Integer">
            <column name="Para_Value" />
        </property>
        <property name="isOpen" type="java.lang.String">
            <column name="Is_Open" length="1" />
        </property>
    </class>
</hibernate-mapping>
